tablevalue/.git/COMMIT_EDITMSG
tablevalue/.git/config
tablevalue/.git/description
tablevalue/.git/HEAD
tablevalue/.git/hooks/applypatch-msg.sample
tablevalue/.git/hooks/commit-msg.sample
tablevalue/.git/hooks/fsmonitor-watchman.sample
tablevalue/.git/hooks/post-update.sample
tablevalue/.git/hooks/pre-applypatch.sample
tablevalue/.git/hooks/pre-commit.sample
tablevalue/.git/hooks/pre-merge-commit.sample
tablevalue/.git/hooks/pre-push.sample
tablevalue/.git/hooks/pre-rebase.sample
tablevalue/.git/hooks/pre-receive.sample
tablevalue/.git/hooks/prepare-commit-msg.sample
tablevalue/.git/hooks/push-to-checkout.sample
tablevalue/.git/hooks/update.sample
tablevalue/.git/index
tablevalue/.git/info/exclude
tablevalue/.git/logs/HEAD
tablevalue/.git/logs/refs/heads/master
tablevalue/.git/logs/refs/remotes/origin/master
tablevalue/.git/objects/09/1d07e9c7528dcf7761f1127f06582ac40236ab
tablevalue/.git/objects/16/7184c2d2fbddb555e65a0815e279b8c024954e
tablevalue/.git/objects/1a/85682771824160d9d84502396e87d8f194404d
tablevalue/.git/objects/2d/a5ac976b1554ee0df959fbc33495d4fdcdeacc
tablevalue/.git/objects/37/1b4907b131bda64921792c81bcd4e30e78ae6d
tablevalue/.git/objects/5f/9769004cea452f08a85a266fe3be7b79d0eff4
tablevalue/.git/objects/89/64be314c90fd75730c9cbb94ac32bdc75c4284
tablevalue/.git/objects/94/819c0d055d1e66382d686ccc7991f3bb261309
tablevalue/.git/objects/96/f5b13d16ddbf65b5c51642fbe934ec2328d6d1
tablevalue/.git/objects/aa/2539ec7fe8a1ff79a47b1f073bf9622d7fdd09
tablevalue/.git/objects/bf/c254d171d9763bb5900820d45f31fa46587634
tablevalue/.git/objects/e1/96388b395330d042e8899c67f9a940a207ba87
tablevalue/.git/objects/f6/a6dfbf666e9454b3b0980f8667b53c552a0dc5
tablevalue/.git/refs/heads/master
tablevalue/.git/refs/remotes/origin/master
tablevalue/.idea/.gitignore
tablevalue/.idea/inspectionProfiles/profiles_settings.xml
tablevalue/.idea/inspectionProfiles/Project_Default.xml
tablevalue/.idea/misc.xml
tablevalue/.idea/modules.xml
tablevalue/.idea/TableValue.iml
tablevalue-0.2.10.dist-info/WHEEL
tablevalue-0.2.10.dist-info/METADATA
tablevalue-0.2.10.dist-info/RECORD
